{
  "type": "GROUP",
"name": "Global Information",
"path": "",
"pathFormatted": "group_missing-name-b06d1",
"stats": {
    "name": "Global Information",
    "numberOfRequests": {
        "total": 60000,
        "ok": 60000,
        "ko": 0
    },
    "minResponseTime": {
        "total": 0,
        "ok": 0,
        "ko": 0
    },
    "maxResponseTime": {
        "total": 7427,
        "ok": 7427,
        "ko": 0
    },
    "meanResponseTime": {
        "total": 394,
        "ok": 394,
        "ko": 0
    },
    "standardDeviation": {
        "total": 1166,
        "ok": 1166,
        "ko": 0
    },
    "percentiles1": {
        "total": 5,
        "ok": 5,
        "ko": 0
    },
    "percentiles2": {
        "total": 9,
        "ok": 9,
        "ko": 0
    },
    "percentiles3": {
        "total": 3796,
        "ok": 3796,
        "ko": 0
    },
    "percentiles4": {
        "total": 4952,
        "ok": 4952,
        "ko": 0
    },
    "group1": {
    "name": "t < 800 ms",
    "count": 53268,
    "percentage": 89
},
    "group2": {
    "name": "800 ms < t < 1200 ms",
    "count": 439,
    "percentage": 1
},
    "group3": {
    "name": "t > 1200 ms",
    "count": 6293,
    "percentage": 10
},
    "group4": {
    "name": "failed",
    "count": 0,
    "percentage": 0
},
    "meanNumberOfRequestsPerSecond": {
        "total": 495.8677685950413,
        "ok": 495.8677685950413,
        "ko": 0
    }
},
"contents": {
"req_wsfaststub-9d162": {
        "type": "REQUEST",
        "name": "WSFastStub",
"path": "WSFastStub",
"pathFormatted": "req_wsfaststub-9d162",
"stats": {
    "name": "WSFastStub",
    "numberOfRequests": {
        "total": 60000,
        "ok": 60000,
        "ko": 0
    },
    "minResponseTime": {
        "total": 0,
        "ok": 0,
        "ko": 0
    },
    "maxResponseTime": {
        "total": 7427,
        "ok": 7427,
        "ko": 0
    },
    "meanResponseTime": {
        "total": 394,
        "ok": 394,
        "ko": 0
    },
    "standardDeviation": {
        "total": 1166,
        "ok": 1166,
        "ko": 0
    },
    "percentiles1": {
        "total": 5,
        "ok": 5,
        "ko": 0
    },
    "percentiles2": {
        "total": 9,
        "ok": 9,
        "ko": 0
    },
    "percentiles3": {
        "total": 3796,
        "ok": 3796,
        "ko": 0
    },
    "percentiles4": {
        "total": 4952,
        "ok": 4952,
        "ko": 0
    },
    "group1": {
    "name": "t < 800 ms",
    "count": 53268,
    "percentage": 89
},
    "group2": {
    "name": "800 ms < t < 1200 ms",
    "count": 439,
    "percentage": 1
},
    "group3": {
    "name": "t > 1200 ms",
    "count": 6293,
    "percentage": 10
},
    "group4": {
    "name": "failed",
    "count": 0,
    "percentage": 0
},
    "meanNumberOfRequestsPerSecond": {
        "total": 495.8677685950413,
        "ok": 495.8677685950413,
        "ko": 0
    }
}
    }
}

}